{
    "categories": [
        {
            "id": 1,
            "parent_id": null,
            "name": "SmartPhone",
            "slug": "smartphone",
            "image": "https://cdn-icons-png.flaticon.com/512/15/15874.png",
            "icon": "fa-mobile",
            "description": "Danh mục điện thoại thông minh",
            "display_order": 1,
            "is_active": true
        },
        {
            "id": 2,
            "parent_id": null,
            "name": "Tablet",
            "slug": "tablet",
            "image": "https://cdn-icons-png.flaticon.com/512/0/191.png",
            "icon": "fa-tablet",
            "description": "Danh mục máy tính bảng",
            "display_order": 2,
            "is_active": true
        },
        {
            "id": 3,
            "parent_id": 1,
            "name": "iPhone",
            "slug": "iphone",
            "image": "https://cdn-icons-png.flaticon.com/512/731/731985.png",
            "icon": "fa-apple",
            "description": "Điện thoại Apple iPhone",
            "display_order": 1,
            "is_active": true
        },
        {
            "id": 4,
            "parent_id": 1,
            "name": "Samsung",
            "slug": "samsung",
            "image": "https://cdn-icons-png.flaticon.com/512/5969/5969129.png",
            "icon": "fa-android",
            "description": "Điện thoại Samsung",
            "display_order": 2,
            "is_active": true
        }
    ],
    "products": [
        {
            "id": 1,
            "category_id": 3,
            "brand_id": 1,
            "name": "iPhone 15 Pro Max",
            "slug": "iphone-15-pro-max",
            "sku": "IP15PM",
            "description": "iPhone cao cấp mới nhất với khung Titanium.",
            "content": "<p>iPhone 15 Pro Max sử dụng chip A17 Pro mạnh mẽ nhất hiện nay.</p>",
            "price": 34990000,
            "sale_price": 32990000,
            "quantity": 50,
            "sold_count": 20,
            "view_count": 150,
            "rating": 5,
            "category": "iPhone",
            "is_featured": true,
            "is_active": true
        },
        {
            "id": 2,
            "category_id": 4,
            "brand_id": 2,
            "name": "Samsung Galaxy S24 Ultra",
            "slug": "samsung-s24-ultra",
            "sku": "SS24U",
            "description": "Quyền năng AI, Camera mắt thần bóng đêm.",
            "content": "<p>Galaxy S24 Ultra tích hợp Galaxy AI và bút S-Pen quyền năng.</p>",
            "price": 31990000,
            "sale_price": 29990000,
            "quantity": 40,
            "sold_count": 15,
            "view_count": 120,
            "rating": 4.8,
            "category": "Samsung",
            "is_featured": true,
            "is_active": true
        },
        {
            "id": 3,
            "category_id": 3,
            "brand_id": 1,
            "name": "iPhone 14 Pro",
            "slug": "iphone-14-pro",
            "sku": "IP14P",
            "description": "Thiết kế Dynamic Island đột phá.",
            "content": "<p>iPhone 14 Pro vẫn là sự lựa chọn tuyệt vời với hiệu năng cao.</p>",
            "price": 27990000,
            "sale_price": 24990000,
            "quantity": 15,
            "sold_count": 100,
            "view_count": 300,
            "rating": 4.5,
            "category": "iPhone",
            "is_featured": false,
            "is_active": true
        },
        {
            "id": 4,
            "category_id": 1,
            "brand_id": 3,
            "name": "Xiaomi 13T Pro 5G",
            "slug": "xiaomi-13t-pro",
            "sku": "MI13TP",
            "description": "Tuyệt tác Camera Leica.",
            "content": "<p>Chiếc điện thoại Xiaomi với ống kính Leica chuyên nghiệp.</p>",
            "price": 16990000,
            "sale_price": 14990000,
            "quantity": 60,
            "sold_count": 5,
            "view_count": 80,
            "rating": 4.2,
            "category": "SmartPhone",
            "is_featured": true,
            "is_active": true
        },
        {
            "id": 5,
            "category_id": 4,
            "brand_id": 2,
            "name": "Samsung Galaxy Z Fold5",
            "slug": "samsung-z-fold-5",
            "sku": "SSFOLD5",
            "description": "Mở ra tiềm năng vô hạn.",
            "content": "<p>Điện thoại gập dẫn đầu xu thế công nghệ.</p>",
            "price": 40990000,
            "sale_price": 36990000,
            "quantity": 10,
            "sold_count": 2,
            "view_count": 200,
            "rating": 5,
            "category": "Samsung",
            "is_featured": true,
            "is_active": true
        },
        {
            "id": 6,
            "category_id": 2,
            "brand_id": 1,
            "name": "iPad Pro 11 inch M2",
            "slug": "ipad-pro-m2",
            "sku": "IPADPRO11",
            "description": "Hiệu năng M2 siêu đỉnh.",
            "content": "<p>Máy tính bảng mạnh mẽ nhất thế giới.</p>",
            "price": 23990000,
            "sale_price": 21990000,
            "quantity": 25,
            "sold_count": 8,
            "view_count": 90,
            "rating": 4.9,
            "category": "Tablet",
            "is_featured": false,
            "is_active": true
        }
    ],
    "product_variants": [
        {
            "id": 1,
            "product_id": 1,
            "sku": "IP15PM-256-BLK",
            "price": 34990000,
            "sale_price": 32990000,
            "quantity": 10,
            "ram": "8GB",
            "rom": "256GB",
            "color": "Black Titanium",
            "image": "https://cdn.tgdd.vn/Products/Images/42/305659/iphone-15-pro-max-black-titanium-1.jpg",
            "is_active": true
        },
        {
            "id": 2,
            "product_id": 1,
            "sku": "IP15PM-256-NAT",
            "price": 34990000,
            "sale_price": 32990000,
            "quantity": 15,
            "ram": "8GB",
            "rom": "256GB",
            "color": "Natural Titanium",
            "image": "https://cdn.tgdd.vn/Products/Images/42/305659/iphone-15-pro-max-tu-nhien-1.jpg",
            "is_active": true
        },
        {
            "id": 3,
            "product_id": 1,
            "sku": "IP15PM-512-NAT",
            "price": 40990000,
            "sale_price": 38990000,
            "quantity": 5,
            "ram": "8GB",
            "rom": "512GB",
            "color": "Natural Titanium",
            "image": "https://cdn.tgdd.vn/Products/Images/42/305659/iphone-15-pro-max-tu-nhien-1.jpg",
            "is_active": true
        },
        {
            "id": 4,
            "product_id": 2,
            "sku": "SS24U-256-GRAY",
            "price": 31990000,
            "sale_price": 29990000,
            "quantity": 20,
            "ram": "12GB",
            "rom": "256GB",
            "color": "Titan Gray",
            "image": "https://encrypted-tbn1.gstatic.com/shopping?q=tbn:ANd9GcTbwqRrki7r0xyk_3b4E_2jvZ-xKKTCLsi8YB44P49z-sFGl_B9GnDqs9I2dHITH9S4AOAGRFEdH-fhacWRA1es4n6pnff06mKIUv60SVc&usqp=CAc",
            "is_active": true
        },
        {
            "id": 5,
            "product_id": 2,
            "sku": "SS24U-512-VIOLET",
            "price": 36990000,
            "sale_price": 33990000,
            "quantity": 10,
            "ram": "12GB",
            "rom": "512GB",
            "color": "Titan Violet",
            "image": "https://happyphone.vn/wp-content/uploads/2024/08/Samsung-Galaxy-Z-Fold5-12GB-512GB.webp",
            "is_active": true
        },
        {
            "id": 6,
            "product_id": 3,
            "sku": "IP14P-128-PUR",
            "price": 27990000,
            "sale_price": 24990000,
            "quantity": 5,
            "ram": "6GB",
            "rom": "128GB",
            "color": "Deep Purple",
            "image": "https://cdn.tgdd.vn/Products/Images/42/251192/iphone-14-pro-max-tim-1.jpg",
            "is_active": true
        },
        {
            "id": 7,
            "product_id": 3,
            "sku": "IP14P-256-GOLD",
            "price": 29990000,
            "sale_price": 27990000,
            "quantity": 8,
            "ram": "6GB",
            "rom": "256GB",
            "color": "Gold",
            "image": "https://bizweb.dktcdn.net/thumb/1024x1024/100/517/334/products/14provang.jpg?v=1716394766760",
            "is_active": true
        },
        {
            "id": 8,
            "product_id": 4,
            "sku": "MI13TP-512-BLUE",
            "price": 16990000,
            "sale_price": 14990000,
            "quantity": 30,
            "ram": "12GB",
            "rom": "512GB",
            "color": "Alpine Blue",
            "image": "https://cdn.tgdd.vn/Products/Images/42/309816/xiaomi-13t-pro-xanh-duong-1.jpg",
            "is_active": true
        },
        {
            "id": 9,
            "product_id": 4,
            "sku": "MI13TP-512-BLK",
            "price": 16990000,
            "sale_price": 14990000,
            "quantity": 20,
            "ram": "12GB",
            "rom": "512GB",
            "color": "Black",
            "image": "https://cdn.tgdd.vn/Products/Images/42/309816/xiaomi-13t-pro-den-1.jpg",
            "is_active": true
        },
        {
            "id": 10,
            "product_id": 5,
            "sku": "SSFOLD5-256-BLUE",
            "price": 40990000,
            "sale_price": 36990000,
            "quantity": 5,
            "ram": "12GB",
            "rom": "256GB",
            "color": "Icy Blue",
            "image": "https://netdeptinhte.vn/wp-content/uploads/2025/02/Samsung-Galaxy-Z-Fold5.jpg",
            "is_active": true
        },
        {
            "id": 11,
            "product_id": 6,
            "sku": "IPAD-M2-128-GRY",
            "price": 23990000,
            "sale_price": 21990000,
            "quantity": 12,
            "ram": "8GB",
            "rom": "128GB",
            "color": "Space Gray",
            "image": "https://cdn.tgdd.vn/Products/Images/522/294103/ipad-pro-m2-11-inch-wifi-xam-1.jpg",
            "is_active": true
        }
    ],
    "product_images": [
        {
            "id": 1,
            "product_id": 1,
            "image_path": "https://cdn.tgdd.vn/Products/Images/42/305659/iphone-15-pro-max-tu-nhien-1.jpg",
            "is_primary": true,
            "display_order": 1
        },
        {
            "id": 2,
            "product_id": 1,
            "image_path": "https://cdn.tgdd.vn/Products/Images/42/305659/iphone-15-pro-max-black-titanium-1.jpg",
            "is_primary": false,
            "display_order": 2
        },
        {
            "id": 3,
            "product_id": 2,
            "image_path": "https://encrypted-tbn1.gstatic.com/shopping?q=tbn:ANd9GcTbwqRrki7r0xyk_3b4E_2jvZ-xKKTCLsi8YB44P49z-sFGl_B9GnDqs9I2dHITH9S4AOAGRFEdH-fhacWRA1es4n6pnff06mKIUv60SVc&usqp=CAc",
            "is_primary": true,
            "display_order": 1
        },
        {
            "id": 4,
            "product_id": 2,
            "image_path": "https://cdn.tgdd.vn/Products/Images/42/307174/samsung-galaxy-s24-ultra-violet-1.jpg",
            "is_primary": false,
            "display_order": 2
        },
        {
            "id": 5,
            "product_id": 3,
            "image_path": "https://happyphone.vn/wp-content/uploads/2024/08/Samsung-Galaxy-Z-Fold5-12GB-512GB.webp",
            "is_primary": true,
            "display_order": 1
        },
        {
            "id": 6,
            "product_id": 4,
            "image_path": "https://cdn.tgdd.vn/Products/Images/42/309816/xiaomi-13t-pro-xanh-duong-1.jpg",
            "is_primary": true,
            "display_order": 1
        },
        {
            "id": 7,
            "product_id": 5,
            "image_path": "https://netdeptinhte.vn/wp-content/uploads/2025/02/Samsung-Galaxy-Z-Fold5.jpg",
            "is_primary": true,
            "display_order": 1
        },
        {
            "id": 8,
            "product_id": 6,
            "image_path": "https://cdn.tgdd.vn/Products/Images/522/294103/ipad-pro-m2-11-inch-wifi-xam-1.jpg",
            "is_primary": true,
            "display_order": 1
        }
    ],
    "reviews": [
        {
            "id": 1,
            "product_id": 1,
            "user_name": "Nguyễn Văn A",
            "rating": 1,
            "comment": "Sản phẩm tuyệt vời, giao hàng nhanh!",
            "created_at": "2024-02-10",
            "avatar": "https://i.pravatar.cc/150?img=1"
        },
        {
            "id": 2,
            "product_id": 1,
            "user_name": "Trần Thị B",
            "rating": 4,
            "comment": "Màu Titan tự nhiên bên ngoài nhìn đẹp hơn.",
            "created_at": "2024-02-09",
            "avatar": "https://i.pravatar.cc/150?img=5"
        },
        {
            "id": 1,
            "product_id": 1,
            "user_name": "Nguyễn Văn A",
            "rating": 1,
            "comment": "Sản phẩm tuyệt vời, giao hàng nhanh!",
            "created_at": "2024-02-10",
            "avatar": "https://i.pravatar.cc/150?img=1"
        },
        {
            "id": 3,
            "product_id": 2,
            "user_name": "Lê C",
            "rating": 5,
            "comment": "Camera zoom 100x đỉnh cao.",
            "created_at": "2024-02-08",
            "avatar": "https://i.pravatar.cc/150?img=8"
        }
    ]
}